git_limiter/__init__.py
git_limiter/backend/__init__.py
git_limiter/backend/base.py
git_limiter/backend/git_subprocess_backend.py
git_limiter/checks/__init__.py
git_limiter/checks/base.py
git_limiter/checks/max_diff.py
git_limiter/cli.py
git_limiter/config/__init__.py
git_limiter/config/settings.py
git_limiter/constants.py
git_limiter/errors.py
git_limiter/parsers/__init__.py
git_limiter/parsers/base.py
git_limiter/parsers/max_diff.py
git_limiter/stats.py
git_limiter/terminal/__init__.py
git_limiter/terminal/base.py
git_limiter/terminal/rich_terminal.py
git_limiter-0.1.1.dist-info/LICENSE.md
git_limiter-0.1.1.dist-info/METADATA
git_limiter-0.1.1.dist-info/WHEEL
git_limiter-0.1.1.dist-info/entry_points.txt
git_limiter-0.1.1.dist-info/RECORD
