Metadata-Version: 2.1
Name: git-limiter
Version: 0.1.1
Summary: Tool allowing to prevent commiting huge diffs
Author: Sergei Konik
Author-email: s.konik.dev@gmail.com
Requires-Python: >=3.8,<4.0
Classifier: Programming Language :: Python :: 3
Classifier: Programming Language :: Python :: 3.8
Classifier: Programming Language :: Python :: 3.9
Classifier: Programming Language :: Python :: 3.10
Classifier: Programming Language :: Python :: 3.11
Requires-Dist: click (>=8.1.3,<9.0.0)
Requires-Dist: rich (>=13.3.3,<14.0.0)
Requires-Dist: tomli (>=2.0.1,<3.0.0)
